MANIFEST.in
README.rst
setup.cfg
setup.py
ubcpi/__init__.py
ubcpi/answer_pool.py
ubcpi/persistence.py
ubcpi/serialize.py
ubcpi/ubcpi.py
ubcpi/utils.py
ubcpi/static/README.txt
ubcpi/static/css/nv.d3.css
ubcpi/static/css/ubcpi.css
ubcpi/static/html/ubcpi.html
ubcpi/static/html/ubcpi_edit.html
ubcpi/static/js/features/cms.feature
ubcpi/static/js/features/installation.feature
ubcpi/static/js/features/render_progress.feature
ubcpi/static/js/features/submit_answers.feature
ubcpi/static/js/features/step_definitions/test_steps.js
ubcpi/static/js/features/support/api.js
ubcpi/static/js/features/support/cat.jpg
ubcpi/static/js/features/support/default_pi.json
ubcpi/static/js/features/support/hooks.js
ubcpi/static/js/page_objects/auto_auth.js
ubcpi/static/js/partials/ubcpi-answer-result.html
ubcpi/static/js/spec/d3-pibar_spec.js
ubcpi/static/js/spec/ubcpi-answer-result-directive_spec.js
ubcpi/static/js/spec/ubcpi-barchar-directive_spec.js
ubcpi/static/js/spec/ubcpi_edit_spec.js
ubcpi/static/js/spec/ubcpi_spec.js
ubcpi/static/js/src/d3-pibar.js
ubcpi/static/js/src/translations.js
ubcpi/static/js/src/ubcpi-answer-result-directive.js
ubcpi/static/js/src/ubcpi-barchart-directive.js
ubcpi/static/js/src/ubcpi.js
ubcpi/static/js/src/ubcpi_edit.js
ubcpi/static/xml/basic_scenario.xml
ubcpi/translations/ar/LC_MESSAGES/text.mo
ubcpi/translations/ar/LC_MESSAGES/text.po
ubcpi/translations/de_DE/LC_MESSAGES/text.mo
ubcpi/translations/de_DE/LC_MESSAGES/text.po
ubcpi/translations/en/LC_MESSAGES/text.mo
ubcpi/translations/en/LC_MESSAGES/text.po
ubcpi/translations/eo/LC_MESSAGES/text.mo
ubcpi/translations/eo/LC_MESSAGES/text.po
ubcpi/translations/es_419/LC_MESSAGES/text.mo
ubcpi/translations/es_419/LC_MESSAGES/text.po
ubcpi/translations/fr/LC_MESSAGES/text.mo
ubcpi/translations/fr/LC_MESSAGES/text.po
ubcpi/translations/fr_CA/LC_MESSAGES/text.mo
ubcpi/translations/fr_CA/LC_MESSAGES/text.po
ubcpi/translations/he/LC_MESSAGES/text.mo
ubcpi/translations/he/LC_MESSAGES/text.po
ubcpi_xblock.egg-info/PKG-INFO
ubcpi_xblock.egg-info/SOURCES.txt
ubcpi_xblock.egg-info/dependency_links.txt
ubcpi_xblock.egg-info/entry_points.txt
ubcpi_xblock.egg-info/requires.txt
ubcpi_xblock.egg-info/top_level.txt